easy_transformers_finetune/__init__.py
easy_transformers_finetune/evaluation.py
easy_transformers_finetune/finetune.py
easy_transformers_finetune/utils.py
easy_transformers_finetune-0.1.0.dist-info/LICENSE.txt
easy_transformers_finetune-0.1.0.dist-info/METADATA
easy_transformers_finetune-0.1.0.dist-info/WHEEL
easy_transformers_finetune-0.1.0.dist-info/top_level.txt
easy_transformers_finetune-0.1.0.dist-info/RECORD
