Metadata-Version: 2.1
Name: easy-transformers-finetune
Version: 0.1.0
Summary: A simple library for fine-tuning transformer models for various NLP tasks.
Home-page: https://github.com/yourusername/easy-transformers-finetune
Author: Your Name
Author-email: your.email@example.com
Classifier: Programming Language :: Python :: 3
Classifier: License :: OSI Approved :: MIT License
Classifier: Operating System :: OS Independent
Requires-Python: >=3.6
License-File: LICENSE.txt
Requires-Dist: transformers >=4.0.0
Requires-Dist: torch >=1.7.0
Requires-Dist: datasets >=1.0.0
Requires-Dist: scikit-learn >=0.24.0
